ogn_parser-0.3.15.dist-info/METADATA
ogn_parser-0.3.15.dist-info/WHEEL
ogn_parser/__init__.py
ogn_parser/ogn_parser.pypy311-pp73-arm-linux-gnu.so
ogn_parser-0.3.15.dist-info/RECORD
