Metadata-Version: 2.4
Name: ogn_parser
Version: 0.3.15
Classifier: Programming Language :: Rust
Classifier: Programming Language :: Python :: Implementation :: CPython
Classifier: Programming Language :: Python :: Implementation :: PyPy
Summary: OGN message parser for Python
Author: Konstantin Gründger <konstantin.gruendger@gmail.com>
Author-email: Konstantin Gründger <konstantin.gruendger@gmail.com>
License: MIT/Apache-2.0
Requires-Python: >=3.9
